Metadata-Version: 2.1
Name: kraken-init
Version: 0.0.28
Summary: kraken-init
Home-page: https://github.com/tactik8/krakeninit
Author: Tactik8
Author-email: info@tactik8.com
License: MIT
Classifier: License :: OSI Approved :: MIT License
Classifier: Programming Language :: Python :: 3
Classifier: Programming Language :: Python :: 3.10
License-File: LICENSE.txt
Requires-Dist: requests
Requires-Dist: flask
